GalaxyTools/__init__.py
GalaxyTools/core.py
galaxytools-0.1.0.dist-info/licenses/LICENSE
galaxytools-0.1.0.dist-info/METADATA
galaxytools-0.1.0.dist-info/WHEEL
galaxytools-0.1.0.dist-info/top_level.txt
galaxytools-0.1.0.dist-info/RECORD
